pyfixm/LICENSE
pyfixm/__init__.py
pyfixm/subs.py
pyfixm-0.1.2.dist-info/LICENSE
pyfixm-0.1.2.dist-info/WHEEL
pyfixm-0.1.2.dist-info/METADATA
pyfixm-0.1.2.dist-info/RECORD
