Metadata-Version: 2.1
Name: pyfixm
Version: 0.1.2
Summary: Parses FIXM data into Python datastructures
Home-page: https://github.com/sync-or-swim/pyfixm
License: BSD-3-Clause
Author: Bryce Beagle
Maintainer: Tyler Compton
Requires-Python: >=3.6,<4.0
Classifier: License :: OSI Approved :: BSD License
Classifier: Operating System :: OS Independent
Classifier: Programming Language :: Python :: 3
Classifier: Programming Language :: Python :: 3.6
Classifier: Programming Language :: Python :: 3.7
Classifier: Programming Language :: Python :: 3.8
Requires-Dist: lxml (>=4.5.0,<5.0.0)
Requires-Dist: six (>=1.14.0,<2.0.0)
Project-URL: Bug Tracker, https://github.com/sync-or-swim/pyfixm/issues
